classcard_dataclient/__init__.py
classcard_dataclient/settings.py
classcard_dataclient/client/__init__.py
classcard_dataclient/client/action.py
classcard_dataclient/client/backbone.py
classcard_dataclient/models/__init__.py
classcard_dataclient/models/album.py
classcard_dataclient/models/base.py
classcard_dataclient/models/clas.py
classcard_dataclient/models/classroom.py
classcard_dataclient/models/course.py
classcard_dataclient/models/meeting_room.py
classcard_dataclient/models/news.py
classcard_dataclient/models/notice.py
classcard_dataclient/models/schedule.py
classcard_dataclient/models/school.py
classcard_dataclient/models/semester.py
classcard_dataclient/models/subject.py
classcard_dataclient/models/user.py
classcard_dataclient/models/video.py
classcard_dataclient/requester/__init__.py
classcard_dataclient/requester/edtech.py
classcard_dataclient/requester/nirvana.py
classcard_dataclient/utils/__init__.py
classcard_dataclient/utils/code.py
classcard_dataclient/utils/constants.py
classcard_dataclient/utils/core.py
classcard_dataclient/utils/data_req.py
classcard_dataclient/utils/dateutils.py
classcard_dataclient/utils/exceptions.py
classcard_dataclient/utils/loggerutils.py
classcard_dataclient/utils/requestutils.py
classcard_dataclient/utils/verification.py
hermes/__init__.py
hermes/config.py
hermes/run.py
hermes/business/__init__.py
hermes/business/pools.py
hermes/business/router.py
hermes/business/profession/__init__.py
hermes/business/profession/action.py
hermes/business/profession/processor.py
hermes/core/__init__.py
hermes/core/mqtt.py
hermes/core/processor.py
hermes/core/worker_pool.py
hermes/models/__init__.py
hermes/models/attendance.py
hermes/models/base.py
hermes/models/clas.py
hermes/models/classroom.py
hermes/models/course.py
hermes/models/device.py
hermes/models/role.py
hermes/models/schedule.py
hermes/models/school.py
hermes/models/subject.py
hermes/requester/__init__.py
hermes/requester/base.py
hermes/requester/nirvana.py
classcard_dataclient-1.1.16.dist-info/LICENSE
classcard_dataclient-1.1.16.dist-info/METADATA
classcard_dataclient-1.1.16.dist-info/WHEEL
classcard_dataclient-1.1.16.dist-info/top_level.txt
classcard_dataclient-1.1.16.dist-info/RECORD
