Metadata-Version: 2.1
Name: classcard-dataclient
Version: 1.1.16
Summary: data client of class card server
Home-page: http://gitlab.h3c.com/edtech/openconnection
Maintainer: Murray
Maintainer-email: ma.yawei@h3c.com
License: MIT
Download-URL: http://gitlab.h3c.com/edtech/openconnection
Keywords: classcard data-client
Platform: Platform Independent
Classifier: Intended Audience :: Developers
Classifier: Topic :: Software Development :: Libraries :: Python Modules
Classifier: Topic :: Internet :: WWW/HTTP :: Dynamic Content :: CGI Tools/Libraries
Classifier: Programming Language :: Python
Classifier: Programming Language :: Python :: 3.5
Classifier: Programming Language :: Python :: 3.6
Requires-Python: >=3.5
Requires-Dist: requests (==2.22.0)
